mypyimagefilters/__init__.py
mypyimagefilters/cpu_image_lib.py
mypyimagefilters/cuda_image_lib.py
mypyimagefilters/openacc_image_lib.py
mypyimagefilters/bin/libfiltersacc.so
mypyimagefilters/bin/libfilterscuda.so
mypyimagefilters/bin/libfiltersseq.so
mypyimagefilters-0.1.3.dist-info/METADATA
mypyimagefilters-0.1.3.dist-info/WHEEL
mypyimagefilters-0.1.3.dist-info/top_level.txt
mypyimagefilters-0.1.3.dist-info/RECORD
