Metadata-Version: 2.4
Name: mypyimagefilters
Version: 0.1.3
Summary: Python wrappers for native image filter libraries (CPU, CUDA, OpenACC).
Author: Ariel
License: MIT
Keywords: image,filters,cuda,openacc,ctypes
Classifier: Programming Language :: Python :: 3
Classifier: License :: OSI Approved :: MIT License
Classifier: Operating System :: POSIX :: Linux
Requires-Python: >=3.8
